Metadata-Version: 2.1
Name: xtelligent-serial
Version: 1.0.47
Summary: Python object serialization focused on JSON
Home-page: https://github.com/xtelligent/xtelligent-serial.git
Author: Xtelligent
Author-email: development@xtelligent.io
License: UNKNOWN
Platform: UNKNOWN
Classifier: Programming Language :: Python :: 3
Classifier: License :: OSI Approved :: MIT License
Classifier: Operating System :: OS Independent
Requires-Python: >=3.7
